tsampling/__init__.py
tsampling/bernoulli.py
tsampling/poisson.py
tsampling/priors.py
tsampling/root.py
tsampling-0.0.1.dist-info/AUTHORS.rst
tsampling-0.0.1.dist-info/LICENSE
tsampling-0.0.1.dist-info/METADATA
tsampling-0.0.1.dist-info/WHEEL
tsampling-0.0.1.dist-info/top_level.txt
tsampling-0.0.1.dist-info/RECORD
