Metadata-Version: 2.1
Name: tsampling
Version: 0.0.1
Summary: A package that implements the Thompson Sampling approach for a Multi-Armed Bandit.
Home-page: https://github.com/dianasargsyan/tsampling.git
Author: Diana Sargsyan
Author-email: diana_sargsyan2@edu.aua.am
License: MIT license
Keywords: tsampling
Classifier: Development Status :: 2 - Pre-Alpha
Classifier: Intended Audience :: Developers
Classifier: License :: OSI Approved :: MIT License
Classifier: Natural Language :: English
Classifier: Programming Language :: Python :: 3
Classifier: Programming Language :: Python :: 3.6
Classifier: Programming Language :: Python :: 3.7
Classifier: Programming Language :: Python :: 3.8
Requires-Python: >=3.6
License-File: LICENSE
License-File: AUTHORS.rst
Requires-Dist: typing
Requires-Dist: numpy
Requires-Dist: seaborn
Requires-Dist: matplotlib
Requires-Dist: pandas
